InfoClimatAPI/InfoClimat.py
InfoClimatAPI/__init__.py
info_climat_api-0.0.1.dist-info/LICENSE
info_climat_api-0.0.1.dist-info/METADATA
info_climat_api-0.0.1.dist-info/WHEEL
info_climat_api-0.0.1.dist-info/top_level.txt
info_climat_api-0.0.1.dist-info/RECORD
