Metadata-Version: 2.1
Name: info-climat-api
Version: 0.0.1
Summary: Api pour les données du site infoclimat
Author-email: lefevre-dev <louislefevre.dev@gmail.com>
License: MIT License
Project-URL: Homepage, https://github.com/lefevre-dev/InfoClimatAPI
Project-URL: Bug Tracker, https://github.com/lefevre-dev/InfoClimatAPI/issues
Classifier: Programming Language :: Python :: 3
Classifier: License :: OSI Approved :: MIT License
Classifier: Operating System :: OS Independent
Requires-Python: >=3.7
License-File: LICENSE
Requires-Dist: requests
